prism/__init__.py
prism/admin.py
prism/constants.py
prism/exceptions.py
prism/main.py
prism/target.py
prism/task.py
prism/utils.py
prism/callbacks/__init__.py
prism/callbacks/callback.py
prism/cli/__init__.py
prism/cli/init.py
prism/client/__init__.py
prism/client/client.py
prism/client/parser.py
prism/client/runner.py
prism/client/visualizer.py
prism/connectors/__init__.py
prism/connectors/base.py
prism/connectors/bigquery.py
prism/connectors/postgres.py
prism/connectors/presto.py
prism/connectors/redshift.py
prism/connectors/snowflake.py
prism/connectors/trino.py
prism/db/__init__.py
prism/db/factory.py
prism/db/mixins.py
prism/db/setup.py
prism/decorators/__init__.py
prism/decorators/target.py
prism/decorators/task.py
prism/docs/__init__.py
prism/docs/build/311ea03002abadcdcaba.png
prism/docs/build/__init__.py
prism/docs/build/ae8a93980ebb6c55123b.ico
prism/docs/build/ce188596011a8fa32931.png
prism/docs/build/d4df11de40d39920ff8c.svg
prism/docs/build/index.html
prism/docs/build/index2.html
prism/docs/build/main.js.LICENSE.txt
prism/engine/__init__.py
prism/engine/compiled_task.py
prism/engine/compiler.py
prism/engine/executor.py
prism/engine/manifest.py
prism/engine/module.py
prism/logging/__init__.py
prism/logging/events.py
prism/logging/execution.py
prism/logging/loggers.py
prism/runtime/__init__.py
prism/runtime/current_run.py
prism/templates/__init__.py
prism/templates/starter_project/.gitignore
prism/templates/starter_project/__init__.py
prism/templates/starter_project/main.py
prism/templates/starter_project/output/.exists
prism/templates/starter_project/tasks/class_task.py
prism/templates/starter_project/tasks/decorated_task.py
prism/tests/__init__.py
prism/tests/integration/__init__.py
prism/tests/integration/integration_utils.py
prism/tests/integration/test_cli.py
prism/tests/integration/test_run.py
prism/tests/integration/test_visualizer.py
prism/tests/integration/additional_package/__init__.py
prism/tests/integration/additional_package/cli_callbacks.py
prism_ds-0.3.0.dist-info/LICENSE
prism_ds-0.3.0.dist-info/METADATA
prism_ds-0.3.0.dist-info/WHEEL
prism_ds-0.3.0.dist-info/entry_points.txt
prism_ds-0.3.0.dist-info/top_level.txt
prism_ds-0.3.0.dist-info/RECORD
