Metadata-Version: 2.1
Name: prism-ds
Version: 0.3.0
Summary: The easiest way to create data pipelines in Python.
Author: prism founders
Author-email: hello@runprism.com
License: Apache-2.0
Project-URL: homepage, https://www.runprism.com
Project-URL: documentation, https://docs.runprism.com
Project-URL: repository, https://github.com/runprism/prism
Platform: unix
Platform: linux
Platform: osx
Platform: win32
Classifier: Programming Language :: Python :: 3
Classifier: Programming Language :: Python :: 3.8
Classifier: Programming Language :: Python :: 3.9
Classifier: Programming Language :: Python :: 3.10
Classifier: Programming Language :: Python :: 3.11
Requires-Python: >=3.7
License-File: LICENSE
Requires-Dist: astor >=0.7
Requires-Dist: boto3 >=1
Requires-Dist: botocore >=1
Requires-Dist: click >=8
Requires-Dist: networkx >=2
Requires-Dist: numpy >=1
Requires-Dist: pandas >=1
Requires-Dist: PyYAML >=6
Requires-Dist: requests >=2
Requires-Dist: Jinja2 ==3.1.2
Requires-Dist: MarkupSafe >=2.0
Requires-Dist: coolname >=2.2
Requires-Dist: shortuuid >=1.0
Requires-Dist: rich-click >=1.6.1
Requires-Dist: Pillow >=9.5.0
Requires-Dist: sqlalchemy >=2.0.27
Requires-Dist: watchdog >=4.0.0
Provides-Extra: bigquery
Requires-Dist: google-api-python-client >=2 ; extra == 'bigquery'
Requires-Dist: google-auth >=2 ; extra == 'bigquery'
Requires-Dist: google-cloud-bigquery >=2 ; extra == 'bigquery'
Requires-Dist: db-dtypes >=1 ; extra == 'bigquery'
Provides-Extra: dev
Requires-Dist: dbt-snowflake <=1.7.5,>=1 ; extra == 'dev'
Requires-Dist: pytest >=7 ; extra == 'dev'
Requires-Dist: fastparquet <1,>=0.8 ; extra == 'dev'
Requires-Dist: tox >=3.24 ; extra == 'dev'
Requires-Dist: mypy >=1.9.0 ; extra == 'dev'
Requires-Dist: tomli >=2.0.1 ; extra == 'dev'
Requires-Dist: typed-ast >=1.5.5 ; extra == 'dev'
Requires-Dist: types-PyYAML >=6.0.12.20240311 ; extra == 'dev'
Requires-Dist: ruff >=0.3.3 ; extra == 'dev'
Requires-Dist: types-networkx >=3.2.1.20240313 ; extra == 'dev'
Requires-Dist: black >=24.3.0 ; extra == 'dev'
Requires-Dist: pre-commit >=3.5.0 ; extra == 'dev'
Provides-Extra: postgres
Requires-Dist: psycopg2-binary >=2.9 ; extra == 'postgres'
Provides-Extra: presto
Requires-Dist: presto-python-client >=0.8 ; extra == 'presto'
Provides-Extra: pyspark
Requires-Dist: pyspark >=3 ; extra == 'pyspark'
Provides-Extra: redshift
Requires-Dist: psycopg2-binary >=2.9 ; extra == 'redshift'
Provides-Extra: snowflake
Requires-Dist: snowflake-connector-python >=2 ; extra == 'snowflake'
Requires-Dist: pyarrow <10.1.0,>=10.0.1 ; extra == 'snowflake'
Provides-Extra: trino
Requires-Dist: trino >=0.319 ; extra == 'trino'
